rlData/__init__.py
rlData/basic.py
rlData/factor.py
rlData/factors.py
rlData/index.py
rlData/stock.py
rlData/factor/__init__.py
rlData/factor/factor.py
rlData/factor/std.py
rlData/factor/vip/__init__.py
rlData/factor/vip/vip.py
rlData/factor/vip/vip_std.py
rlData/utils/__init__.py
rlData/utils/client.py
rlData/utils/tools.py
rlData-0.3.0.dist-info/METADATA
rlData-0.3.0.dist-info/WHEEL
rlData-0.3.0.dist-info/top_level.txt
rlData-0.3.0.dist-info/RECORD
