Metadata-Version: 2.1
Name: rlData
Version: 0.3.0
Summary: 融量数据接口
Home-page: UNKNOWN
Author: joyle
Author-email: joyle.zhang@qq.com
License: UNKNOWN
Platform: UNKNOWN
Classifier: Programming Language :: Python :: 3
Classifier: License :: OSI Approved :: MIT License
Classifier: Operating System :: OS Independent
Requires-Dist: pandas (>=0.24.2)
